LICENSE
MANIFEST.in
README.rst
pyproject.toml
requirements.txt
setup.cfg
setup.py
django_nets_core.egg-info/PKG-INFO
django_nets_core.egg-info/SOURCES.txt
django_nets_core.egg-info/dependency_links.txt
django_nets_core.egg-info/requires.txt
django_nets_core.egg-info/top_level.txt
nets_core/__init__.py
nets_core/admin.py
nets_core/apps.py
nets_core/asgi.py
nets_core/auth_urls.py
nets_core/celery.py
nets_core/decorators.py
nets_core/default_settings.py
nets_core/firebase_messages.py
nets_core/google_auth.py
nets_core/handlers.py
nets_core/listeners.py
nets_core/mail.py
nets_core/manage.py
nets_core/models.py
nets_core/params.py
nets_core/responses.py
nets_core/security.py
nets_core/serializers.py
nets_core/settings.py
nets_core/settings_nets.py
nets_core/tasks.py
nets_core/urls.py
nets_core/utils.py
nets_core/views.py
nets_core/wsgi.py
nets_core/management/commands/__init__.py
nets_core/management/commands/nets-settings.py
nets_core/management/commands/test_push_notification.py
nets_core/management/commands/__pycache__/__init__.cpython-312.pyc
nets_core/management/commands/__pycache__/nets-settings.cpython-312.pyc
nets_core/management/commands/__pycache__/test_push_notification.cpython-312.pyc
nets_core/middleware/auth_token.py
nets_core/middleware/__pycache__/auth_token.cpython-312.pyc
nets_core/migrations/0001_initial.py
nets_core/migrations/0002_alter_verificationcode_token.py
nets_core/migrations/0003_userdevice.py
nets_core/migrations/0004_remove_userdevice_device_id_userdevice_uuid.py
nets_core/migrations/0005_userdevice_uuid.py
nets_core/migrations/0006_verificationcode_device.py
nets_core/migrations/0007_alter_verificationcode_device.py
nets_core/migrations/0008_verificationcode_ip_userfirebasenotification.py
nets_core/migrations/0009_userdevice_ip.py
nets_core/migrations/0010_permission_role_userrole_and_more.py
nets_core/migrations/0011_role_enabled.py
nets_core/migrations/0012_permission_created_permission_updated_role_created_and_more.py
nets_core/migrations/0013_customemail_updated_fields_and_more.py
nets_core/migrations/0014_rolepermission_remove_permission_permission_index_and_more.py
nets_core/migrations/__init__.py
