Metadata-Version: 2.1
Name: django-nets-core
Version: 0.2.18
Summary: A lazy API rest request handler.
Home-page: https://github.com/esbozos/django-nets-core
Author: Norman Torres
Author-email: norman.nets@gmail.com
License: BSD-3-Clause
Classifier: Environment :: Web Environment
Classifier: Framework :: Django
Classifier: Framework :: Django :: 5.0
Classifier: Intended Audience :: Developers
Classifier: License :: OSI Approved :: BSD License
Classifier: Operating System :: OS Independent
Classifier: Programming Language :: Python
Classifier: Programming Language :: Python :: 3
Classifier: Programming Language :: Python :: 3 :: Only
Classifier: Programming Language :: Python :: 3.8
Classifier: Programming Language :: Python :: 3.9
Classifier: Programming Language :: Python :: 3.10
Classifier: Programming Language :: Python :: 3.12
Classifier: Topic :: Internet :: WWW/HTTP
Classifier: Topic :: Internet :: WWW/HTTP :: Dynamic Content
Requires-Python: >=3.8
License-File: LICENSE
Requires-Dist: Django>=5.1.4
Requires-Dist: google-auth>=2.3.0
Requires-Dist: pytz>=2024.1
Requires-Dist: python-dateutil>=2.9.0.post0
Requires-Dist: shortuuid>=1.0.13
Requires-Dist: django-oauth-toolkit>=2.4.0
Requires-Dist: firebase-admin>=6.5.0
Requires-Dist: celery>=5.4.0
Requires-Dist: django-cors-headers>=4.4.0
Requires-Dist: pymemcache>=4.0.0
Requires-Dist: python-memcached>=1.62
Requires-Dist: django-memcached>=0.1.2
Requires-Dist: channels>=4.1.0
Requires-Dist: channels-redis>=4.2.0
Requires-Dist: daphne>=4.1.2
